odoo10_addon_account_banking_fr_lcr-10.0.1.0.0.99.dev11-py2.7-nspkg.pth
odoo/addons/account_banking_fr_lcr/README.rst
odoo/addons/account_banking_fr_lcr/__init__.py
odoo/addons/account_banking_fr_lcr/__manifest__.py
odoo/addons/account_banking_fr_lcr/post_install.py
odoo/addons/account_banking_fr_lcr/data/account_payment_method.xml
odoo/addons/account_banking_fr_lcr/demo/lcr_demo.xml
odoo/addons/account_banking_fr_lcr/i18n/account_banking_fr_lcr.pot
odoo/addons/account_banking_fr_lcr/i18n/fr.po
odoo/addons/account_banking_fr_lcr/i18n/nb_NO.po
odoo/addons/account_banking_fr_lcr/models/__init__.py
odoo/addons/account_banking_fr_lcr/models/account_move_line.py
odoo/addons/account_banking_fr_lcr/models/account_payment_order.py
odoo/addons/account_banking_fr_lcr/static/description/icon.png
odoo10_addon_account_banking_fr_lcr-10.0.1.0.0.99.dev11.dist-info/METADATA
odoo10_addon_account_banking_fr_lcr-10.0.1.0.0.99.dev11.dist-info/RECORD
odoo10_addon_account_banking_fr_lcr-10.0.1.0.0.99.dev11.dist-info/WHEEL
odoo10_addon_account_banking_fr_lcr-10.0.1.0.0.99.dev11.dist-info/namespace_packages.txt
odoo10_addon_account_banking_fr_lcr-10.0.1.0.0.99.dev11.dist-info/top_level.txt
